pycodesearch/__init__.py
pycodesearch/cli.py
pycodesearch/types.py
pycodesearch-0.1.4.dist-info/entry_points.txt
pycodesearch-0.1.4.dist-info/LICENSE
pycodesearch-0.1.4.dist-info/WHEEL
pycodesearch-0.1.4.dist-info/METADATA
pycodesearch-0.1.4.dist-info/RECORD
